{
  "DisplayName": "Main",
  "Tooltip": null,
  "HelpLink": null,
  "Color": null,
  "OriginalIconFileName": null,
  "Arguments": [
    {
      "Name": "DTSecondChaserPCL",
      "DisplayName": "DTSecondChaserPCL",
      "Category": null,
      "Tooltip": null,
      "Placeholder": null,
      "Widget": null,
      "IsRequired": true,
      "IsPrincipal": true,
      "ArgumentType": 0,
      "DataSourceItems": null
    },
    {
      "Name": "DTFirstChaserPCL",
      "DisplayName": "DTFirstChaserPCL",
      "Category": null,
      "Tooltip": null,
      "Placeholder": null,
      "Widget": null,
      "IsRequired": true,
      "IsPrincipal": true,
      "ArgumentType": 0,
      "DataSourceItems": null
    },
    {
      "Name": "DTOver5kDDM",
      "DisplayName": "DTOver5kDDM",
      "Category": null,
      "Tooltip": null,
      "Placeholder": null,
      "Widget": null,
      "IsRequired": true,
      "IsPrincipal": true,
      "ArgumentType": 0,
      "DataSourceItems": null
    },
    {
      "Name": "DTUnder5kDDM",
      "DisplayName": "DTUnder5kDDM",
      "Category": null,
      "Tooltip": null,
      "Placeholder": null,
      "Widget": null,
      "IsRequired": true,
      "IsPrincipal": true,
      "ArgumentType": 0,
      "DataSourceItems": null
    }
  ]
}